[
	{
		"rank": 9,
		"waku": "枠5黄",
		"umaban": 10,
		"horse": "アドマイヤベル",
		"age": "牝3",
		"weight": "55.0",
		"jockey": "横山 武史",
		"time": "2:25.0",
		"margin": "クビ",
		"h_weight": 484,
		"h_weight_zougen": 0,
		"f_time": "35.1",
		"trainer": "加藤 征弘",
		"pop": "8",
		"corner": [
			7,
			7,
			6,
			6
		],
		"title": "オークス"
	},
	{
		"rank": 1,
		"waku": "枠5黄",
		"umaban": 8,
		"horse": "アドマイヤベル",
		"age": "牝3",
		"weight": "55.0",
		"jockey": "横山 武史",
		"time": "1:59.0",
		"margin": "",
		"h_weight": 484,
		"h_weight_zougen": 0,
		"f_time": "34.2",
		"trainer": "加藤 征弘",
		"pop": "2",
		"corner": [
			5,
			6,
			6
		],
		"title": "サンケイスポーツ賞フローラステークス"
	}
]