[
	{
		"rank": 5,
		"waku": "枠7橙",
		"umaban": 10,
		"horse": "エマヌエーレ",
		"age": "牡3",
		"weight": "56.0",
		"jockey": "和田 竜二",
		"time": "1:47.0",
		"margin": "アタマ",
		"h_weight": 484,
		"h_weight_zougen": -12,
		"f_time": "35.7",
		"trainer": "平田 修",
		"pop": "9",
		"corner": [
			3,
			3
		],
		"title": "毎日杯"
	},
	{
		"rank": 14,
		"waku": "枠8桃",
		"umaban": 15,
		"horse": "エマヌエーレ",
		"age": "牡3",
		"weight": "54.0",
		"jockey": "石橋 脩",
		"time": "1:48.2",
		"margin": "１ 1/4",
		"h_weight": 490,
		"h_weight_zougen": 6,
		"f_time": "36.1",
		"trainer": "平田 修",
		"pop": "14",
		"corner": [
			4,
			5,
			5,
			5
		],
		"title": "ラジオNIKKEI賞"
	}
]