[
	{
		"rank": 3,
		"waku": "枠1白",
		"umaban": 1,
		"horse": "エンドレスサマー",
		"age": "牡2",
		"weight": "55.0",
		"jockey": "横山 和生",
		"time": "1:09.4",
		"margin": "アタマ",
		"h_weight": 500,
		"h_weight_zougen": 8,
		"f_time": "35.1",
		"trainer": "上原 佑紀",
		"pop": "2",
		"corner": [
			2,
			2
		],
		"title": "函館2歳ステークス"
	},
	{
		"rank": 6,
		"waku": "枠8桃",
		"umaban": 13,
		"horse": "エンドレスサマー",
		"age": "牡2",
		"weight": "55.0",
		"jockey": "岩田 望来",
		"time": "1:09.8",
		"margin": "１",
		"h_weight": 492,
		"h_weight_zougen": -8,
		"f_time": "34.4",
		"trainer": "上原 佑紀",
		"pop": "4",
		"corner": [
			10,
			9
		],
		"title": "小倉2歳ステークス"
	}
]