[
	{
		"rank": 12,
		"waku": "枠8桃",
		"umaban": 15,
		"horse": "スルーセブンシーズ",
		"age": "牝5",
		"weight": "56.0",
		"jockey": "池添 謙一",
		"time": "2:31.8",
		"margin": "クビ",
		"h_weight": 456,
		"h_weight_zougen": null,
		"f_time": "35.4",
		"trainer": "尾関 知人",
		"pop": "3",
		"corner": [
			6,
			6,
			5,
			6
		],
		"title": "有馬記念"
	},
	{
		"rank": 2,
		"waku": "枠3赤",
		"umaban": 6,
		"horse": "スルーセブンシーズ",
		"age": "牝5",
		"weight": "56.0",
		"jockey": "池添 謙一",
		"time": "2:11.2",
		"margin": "クビ",
		"h_weight": 446,
		"h_weight_zougen": -2,
		"f_time": "34.6",
		"trainer": "尾関 知人",
		"pop": "10",
		"corner": [
			17,
			17,
			16,
			12
		],
		"title": "宝塚記念"
	},
	{
		"rank": 1,
		"waku": "枠5黄",
		"umaban": 8,
		"horse": "スルーセブンシーズ",
		"age": "牝5",
		"weight": "54.0",
		"jockey": "C.ルメール",
		"time": "1:46.5",
		"margin": "",
		"h_weight": 448,
		"h_weight_zougen": 4,
		"f_time": "33.8",
		"trainer": "尾関 知人",
		"pop": "2",
		"corner": [
			9,
			9,
			8,
			5
		],
		"title": "ローレル競馬場賞中山牝馬ステークス"
	}
]