[
	{
		"rank": 5,
		"waku": "枠6緑",
		"umaban": 11,
		"horse": "ボルザコフスキー",
		"age": "牡5",
		"weight": "57.0",
		"jockey": "B.ムルザバエフ",
		"time": "1:22.0",
		"margin": "２ 1/2",
		"h_weight": 512,
		"h_weight_zougen": -2,
		"f_time": "35.9",
		"trainer": "清水 久詞",
		"pop": "7",
		"corner": [
			14,
			12
		],
		"title": "阪急杯"
	},
	{
		"rank": 9,
		"waku": "枠8桃",
		"umaban": 16,
		"horse": "ボルザコフスキー",
		"age": "牡5",
		"weight": "57.0",
		"jockey": "吉村 誠之助",
		"time": "1:33.7",
		"margin": "クビ",
		"h_weight": 512,
		"h_weight_zougen": 0,
		"f_time": "35.3",
		"trainer": "清水 久詞",
		"pop": "10",
		"corner": [
			17,
			12
		],
		"title": "読売マイラーズカップ"
	}
]