[
	{
		"rank": 2,
		"waku": "枠5黄",
		"umaban": 10,
		"horse": "メイクアスナッチ",
		"age": "牝3",
		"weight": "54.0",
		"jockey": "戸崎 圭太",
		"time": "1:34.3",
		"margin": "アタマ",
		"h_weight": 436,
		"h_weight_zougen": 6,
		"f_time": "35.3",
		"trainer": "武市 康男",
		"pop": "7",
		"corner": [
			13,
			10,
			9
		],
		"title": "フェアリーステークス"
	},
	{
		"rank": 11,
		"waku": "枠7橙",
		"umaban": 13,
		"horse": "メイクアスナッチ",
		"age": "牝3",
		"weight": "54.0",
		"jockey": "戸崎 圭太",
		"time": "1:34.5",
		"margin": "ハナ",
		"h_weight": 432,
		"h_weight_zougen": -4,
		"f_time": "36.2",
		"trainer": "武市 康男",
		"pop": "6",
		"corner": [
			9,
			6,
			8
		],
		"title": "ニュージーランドトロフィー"
	}
]