{
    "title": "東京新聞杯",
    "url": "https://www.jra.go.jp/datafile/seiseki/replay/2023/012.html",
    "horse": [
        {
            "name": "プレサージュリフト",
            "rank": 1
        },
        {
            "name": "ピンハイ",
            "rank": 2
        },
        {
            "name": "ナミュール",
            "rank": 3
        },
        {
            "name": "エアロロノア",
            "rank": 4
        },
        {
            "name": "ファルコニア",
            "rank": 5
        },
        {
            "name": "インダストリア",
            "rank": 6
        },
        {
            "name": "ショウナンマグマ",
            "rank": 7
        },
        {
            "name": "ウインカーネリアン",
            "rank": 8
        },
        {
            "name": "マテンロウオリオン",
            "rank": 9
        },
        {
            "name": "プリンスリターン",
            "rank": 10
        },
        {
            "name": "シュリ",
            "rank": 11
        },
        {
            "name": "タイムトゥヘヴン",
            "rank": 12
        },
        {
            "name": "ジャスティンカフェ",
            "rank": 13
        },
        {
            "name": "サクラトゥジュール",
            "rank": 14
        },
        {
            "name": "カイザーミノル",
            "rank": 15
        },
        {
            "name": "ピースワンパラディ",
            "rank": 16
        }
    ]
}