{
    "title": "プロキオンステークス",
    "url": "https://www.jra.go.jp/datafile/seiseki/replay/2023/061.html",
    "horse": [
        {
            "name": "ジレトール",
            "rank": 1
        },
        {
            "name": "フルム",
            "rank": 2
        },
        {
            "name": "タガノビューティー",
            "rank": 3
        },
        {
            "name": "メイショウテンスイ",
            "rank": 4
        },
        {
            "name": "アティード",
            "rank": 5
        },
        {
            "name": "オーヴァーネクサス",
            "rank": 6
        },
        {
            "name": "オメガレインボー",
            "rank": 7
        },
        {
            "name": "ブルベアイリーデ",
            "rank": 8
        },
        {
            "name": "イフティファール",
            "rank": 9
        },
        {
            "name": "ドンフランキー",
            "rank": 10
        },
        {
            "name": "ロイヤルパールス",
            "rank": 11
        },
        {
            "name": "ケイアイターコイズ",
            "rank": 12
        },
        {
            "name": "エルバリオ",
            "rank": 13
        },
        {
            "name": "メイショウダジン",
            "rank": 14
        },
        {
            "name": "リメイク",
            "rank": 15
        }
    ]
}