{
    "title": "アイルランドトロフィー府中牝馬ステークス",
    "url": "https://www.jra.go.jp/datafile/seiseki/replay/2023/092.html",
    "horse": [
        {
            "name": "シンリョクカ",
            "rank": 1
        },
        {
            "name": "エリカヴィータ",
            "rank": 2
        },
        {
            "name": "コスタボニータ",
            "rank": 3
        },
        {
            "name": "ディヴィーナ",
            "rank": 4
        },
        {
            "name": "プレサージュリフト",
            "rank": 5
        },
        {
            "name": "ルージュスティリア",
            "rank": 6
        },
        {
            "name": "フィアスプライド",
            "rank": 7
        },
        {
            "name": "アンドヴァラナウト",
            "rank": 8
        },
        {
            "name": "ファユエン",
            "rank": 9
        },
        {
            "name": "ライラック",
            "rank": 10
        },
        {
            "name": "イズジョーノキセキ",
            "rank": 11
        },
        {
            "name": "ルージュエヴァイユ",
            "rank": 12
        }
    ]
}